{
  "_meta": {
    "sources": [
      "loopback/common/models",
      "../api/models"
    ],
    "mixins": [
      "loopback/common/mixins",
      "loopback/api/mixins",
      "../common/mixins",
      "./mixins"
    ]
  },
  "AccessToken": {
    "dataSource": "mongoDs",
    "public": false,
    "relations": {
      "user": {
        "type": "belongsTo",
        "model": "user",
        "foreignKey": "userId"
      }
    }
  },
  "ACL": {
    "dataSource": "mongoDs",
    "public": false
  },
  "Category": {
    "dataSource": "mongoDs",
    "public": false
  },
  "Type": {
    "dataSource": "mongoDs",
    "public": true
  },
  "user": {
    "dataSource": "mongoDs",
    "public": true
  },
  "Post": {
    "dataSource": "mongoDs",
    "public": true
  }
}
